odoo/addons/web_widget_image_webcam/README.rst
odoo/addons/web_widget_image_webcam/__init__.py
odoo/addons/web_widget_image_webcam/__manifest__.py
odoo/addons/web_widget_image_webcam/i18n/web_widget_image_webcam.pot
odoo/addons/web_widget_image_webcam/models/__init__.py
odoo/addons/web_widget_image_webcam/models/ir_config_parameter.py
odoo/addons/web_widget_image_webcam/static/description/icon.png
odoo/addons/web_widget_image_webcam/static/src/css/web_widget_image_webcam.css
odoo/addons/web_widget_image_webcam/static/src/img/webcam_placeholder.png
odoo/addons/web_widget_image_webcam/static/src/js/webcam.swf
odoo/addons/web_widget_image_webcam/static/src/js/webcam_widget.js
odoo/addons/web_widget_image_webcam/static/src/lib/webcam.js
odoo/addons/web_widget_image_webcam/static/src/xml/web_widget_image_webcam.xml
odoo/addons/web_widget_image_webcam/views/assets.xml
odoo11_addon_web_widget_image_webcam-11.0.1.0.0.99.dev4.dist-info/METADATA
odoo11_addon_web_widget_image_webcam-11.0.1.0.0.99.dev4.dist-info/WHEEL
odoo11_addon_web_widget_image_webcam-11.0.1.0.0.99.dev4.dist-info/top_level.txt
odoo11_addon_web_widget_image_webcam-11.0.1.0.0.99.dev4.dist-info/RECORD
